lytics/__init__.py
lytics/main.py
lytics_smm_demo-0.1.1.dist-info/METADATA
lytics_smm_demo-0.1.1.dist-info/WHEEL
lytics_smm_demo-0.1.1.dist-info/top_level.txt
lytics_smm_demo-0.1.1.dist-info/RECORD
