Metadata-Version: 2.1
Name: lytics-smm-demo
Version: 0.1.1
Summary: A Python package for interacting with the Lytics SMM API
Home-page: https://github.com/accesstokens/lytics-smm-demo
Author: Lytics SMM
Requires-Python: >=3.6
Requires-Dist: requests
